mcp_image_gen/__init__.py
mcp_image_gen/__main__.py
mcp_image_gen-0.1.3.dist-info/licenses/LICENSE
mcp_image_gen-0.1.3.dist-info/METADATA
mcp_image_gen-0.1.3.dist-info/WHEEL
mcp_image_gen-0.1.3.dist-info/entry_points.txt
mcp_image_gen-0.1.3.dist-info/top_level.txt
mcp_image_gen-0.1.3.dist-info/RECORD
