Metadata-Version: 2.4
Name: mcp-image-gen
Version: 0.1.3
Summary: 一个基于MCP协议的OpenAI图像生成服务器，生成后上传图床
Home-page: https://github.com/yourusername/mcp-image-gen
Author: MCP服务开发者
Author-email: your.email@example.com
Classifier: Programming Language :: Python :: 3
Classifier: License :: OSI Approved :: MIT License
Classifier: Operating System :: OS Independent
Classifier: Topic :: Software Development :: Libraries :: Python Modules
Classifier: Intended Audience :: Developers
Requires-Python: >=3.7
License-File: LICENSE
Requires-Dist: mcp>=1.6.0
Requires-Dist: requests>=2.25.0
Dynamic: author
Dynamic: author-email
Dynamic: classifier
Dynamic: description
Dynamic: description-content-type
Dynamic: home-page
Dynamic: license-file
Dynamic: requires-dist
Dynamic: requires-python
Dynamic: summary
